Metadata-Version: 2.1
Name: wordvecpy
Version: 0.71
Summary: Package for working with word vector embeddings
Home-page: https://github.com/metriczulu/wordvecpy
Author: Shane Stephenson
Author-email: stephenson.shane.a@gmail.com
License: All yours bro
Download-URL: https://github.com/metriczulu/wordvecpy/archive/v0.71.tar.gz
Platform: UNKNOWN
